qudt/__init__.py
qudt/multiplier.py
qudt/ontology/__init__.py
qudt/ontology/ontology_reader.py
qudt/ontology/ontology_utils.py
qudt/ontology/qudt.py
qudt/ontology/rdf.py
qudt/ontology/rdfs.py
qudt/ontology/resources/__init__.py
qudt/ontology/resources/contrib.jsonld
qudt/ontology/resources/dimension.rdf
qudt/ontology/resources/dtype.rdf
qudt/ontology/resources/openphacts.jsonld
qudt/ontology/resources/openphacts.ttl
qudt/ontology/resources/quantity.rdf
qudt/ontology/resources/qudt-quantity.rdf
qudt/ontology/resources/qudt.jsonld
qudt/ontology/resources/qudt.rdf
qudt/ontology/resources/unit.jsonld
qudt/ontology/resources/unit.rdf
qudt/ontology/unit_factory.py
qudt/py.typed
qudt/quantity.py
qudt/unit.py
qudt/units/__init__.py
qudt/units/area.py
qudt/units/concentration.py
qudt/units/counting.py
qudt/units/dimensionless.py
qudt/units/energy.py
qudt/units/information.py
qudt/units/length.py
qudt/units/mass.py
qudt/units/temperature.py
qudt/units/volume.py
qudt/uo/__init__.py
qudt/uo/unit_ontology_factory.py
pyqudt-1.1.1.dist-info/LICENSE
pyqudt-1.1.1.dist-info/WHEEL
pyqudt-1.1.1.dist-info/METADATA
pyqudt-1.1.1.dist-info/RECORD
